Metadata-Version: 2.1
Name: etiopique-lorem-texts
Version: 0.1.0
Summary: A simple Lorem Ipsum generator for Amharic and English.
Home-page: https://github.com/mitegab/etiopique_lorem_texts.git
Author: mitegab
Author-email: miteabebe60@gmail.com
Classifier: Programming Language :: Python :: 3
Classifier: License :: OSI Approved :: MIT License
Classifier: Operating System :: OS Independent
Requires-Python: >=3.6
